music_api/__init__.py
music_api/_template.py
music_api/user_agents.txt
music_api/utils.py
music_api/kg/__init__.py
music_api/kg/_kg.py
music_api/kw/__init__.py
music_api/kw/_kw.py
music_api/lib/AES.py
music_api/lib/RSA.py
music_api/mg/__init__.py
music_api/mg/_mg.py
music_api/qianqian/__init__.py
music_api/qianqian/_qianqian.py
music_api/wyy/__init__.py
music_api/wyy/_wyy.py
pymusicapi-0.1.1.dist-info/METADATA
pymusicapi-0.1.1.dist-info/WHEEL
pymusicapi-0.1.1.dist-info/top_level.txt
pymusicapi-0.1.1.dist-info/RECORD
