Metadata-Version: 2.1
Name: pymusicapi
Version: 0.1.1
Summary: music apis
Author: kewuaa
Project-URL: GitHub, https://github.com/kewuaa/music_api
Requires-Dist: aiohttp
Requires-Dist: aiofiles
Requires-Dist: rsa
Requires-Dist: pycryptodome
Requires-Dist: lxml
Requires-Dist: qrcode
